LICENSE
MANIFEST.in
README.md
setup.cfg
setup.py
stdeb.cfg
./oathldap_srv/__about__.py
./oathldap_srv/__init__.py
./oathldap_srv/bind_proxy.py
./oathldap_srv/cfg.py
./oathldap_srv/logger.py
./oathldap_srv/hotp_validator/__init__.py
./oathldap_srv/hotp_validator/__main__.py
./oathldap_srv/hotp_validator/cfg.py
./oathldap_srv/hotp_validator/handler.py
./oathldap_srv/hotp_validator/server.py
oath_ldap_srv.egg-info/PKG-INFO
oath_ldap_srv.egg-info/SOURCES.txt
oath_ldap_srv.egg-info/dependency_links.txt
oath_ldap_srv.egg-info/not-zip-safe
oath_ldap_srv.egg-info/requires.txt
oath_ldap_srv.egg-info/top_level.txt